MedDataKit/data_pipe_routines/__init__.py
MedDataKit/data_pipe_routines/data_encoding_routines.py
MedDataKit/data_pipe_routines/data_type_routines.py
MedDataKit/data_pipe_routines/missing_data_routines.py
MedDataKit/dataset/base_dataset.py
MedDataKit/dataset/base_ml_task_dataset.py
MedDataKit/dataset/base_raw_dataset.py
MedDataKit/dataset/bioinfo_dataset.py
MedDataKit/dataset/clinical_dataset.py
MedDataKit/dataset/medical_dataset.py
MedDataKit/dataset/repo_dataset.py
MedDataKit/dataset/survey_dataset.py
MedDataKit/downloader.py
MedDataKit/prediction/prediction.py
MedDataKit/utils.py
meddatakit-0.0.12.dist-info/METADATA
meddatakit-0.0.12.dist-info/WHEEL
meddatakit-0.0.12.dist-info/RECORD
